Workbook

Sheet Working
B1: Column Labels
B2: Sum of Debit | D2: Sum of Credit | F2: Total Sum of Debit | G2: Total Sum of Credit
A3: NetSuite GL# | B3: 46207 | C3: 46221 | D3: 46207 | E3: 46221 | H3: PTD | I3: ADP Department Title | J3: Netsuite GL Account Name | K3: Income Statement Account Name | L3: NS Income balance
A4: 60000OT | B4: 82.22 | C4: 72.69 | D4: 0 | E4: 0 | F4: 154.91 | G4: 0 | H4: =+B4+C4 -> 154.91 | I4: =+VLOOKUP(A4,[1]Final!$A:$E,5,0) -> Night Audit | J4: =+VLOOKUP(A4,[1]Final!$A:$G,7,0) -> Night Auditor Overtime | K4: Front Desk | L4: =+VLOOKUP($A4,IncomeStatement!$A:$F,6,0) -> 356.01
A5: 60000R | B5: 4558.08 | C5: 4220.41 | D5: 0 | E5: 0 | F5: 8778.49 | G5: 0 | H5: =+B5+C5 -> 8778.49 | I5: =+VLOOKUP(A5,[1]Final!$A:$E,5,0) -> Night Audit | J5: =+VLOOKUP(A5,[1]Final!$A:$G,7,0) -> Night Auditor Regular Pay | K5: Front Desk | L5: =+VLOOKUP($A5,IncomeStatement!$A:$F,6,0) -> #N/A
A6: 60010R | B6: 2624.51 | C6: 3394.89 | D6: 0 | E6: 0 | F6: 6019.4 | G6: 0 | H6: =+B6+C6 -> 6019.4 | I6: =+VLOOKUP(A6,[1]Final!$A:$E,5,0) -> Guest Service Management | J6: =+VLOOKUP(A6,[1]Final!$A:$G,7,0) -> Guest Service Manager Regular Pay | K6: Management | L6: =+VLOOKUP($A6,IncomeStatement!$A:$F,6,0) -> #N/A
A7: 60020R | B7: 3824.62 | C7: 4315.39 | D7: 0 | E7: 0 | F7: 8140.01 | G7: 0 | H7: =+B7+C7 -> 8140.01 | I7: =+VLOOKUP(A7,[1]Final!$A:$E,5,0) -> Rooms Division Manager | J7: =+VLOOKUP(A7,[1]Final!$A:$G,7,0) -> Rooms Division Manager Regular Pay | K7: Management | L7: =+VLOOKUP($A7,IncomeStatement!$A:$F,6,0) -> #N/A
A8: 60040OT | B8: 0.87 | C8: 24.64 | D8: 0 | E8: 0 | F8: 25.51 | G8: 0 | H8: =+B8+C8 -> 25.51 | I8: =+VLOOKUP(A8,[1]Final!$A:$E,5,0) -> Guest Service Supervisor | J8: =+VLOOKUP(A8,[1]Final!$A:$G,7,0) -> Guest Service Supervisor Overtime | K8: Guest Services | L8: =+VLOOKUP($A8,IncomeStatement!$A:$F,6,0) -> 182.38
A9: 60040R | B9: 2673.13 | C9: 2387.51 | D9: 0 | E9: 0 | F9: 5060.64 | G9: 0 | H9: =+B9+C9 -> 5060.64 | I9: =+VLOOKUP(A9,[1]Final!$A:$E,5,0) -> Guest Service Supervisor | J9: =+VLOOKUP(A9,[1]Final!$A:$G,7,0) -> Guest Service Supervisor Regular Pay | K9: Guest Services | L9: =+VLOOKUP($A9,IncomeStatement!$A:$F,6,0) -> #N/A
A10: 60050R | B10: 7748.01 | C10: 7663.18 | D10: 0 | E10: 0 | F10: 15411.19 | G10: 0 | H10: =+B10+C10 -> 15411.19 | I10: =+VLOOKUP(A10,[1]Final!$A:$E,5,0) -> Guest Service Representatives | J10: =+VLOOKUP(A10,[1]Final!$A:$G,7,0) -> Guest Service Representatives Regular Pay | K10: Guest Services | L10: =+VLOOKUP($A10,IncomeStatement!$A:$F,6,0) -> #N/A
A11: 60200OT | C11: 142.51 | E11: 0 | F11: 142.51 | G11: 0 | H11: =+B11+C11 -> 142.51 | I11: =+VLOOKUP(A11,[1]Final!$A:$E,5,0) -> Concierge | J11: =+VLOOKUP(A11,[1]Final!$A:$G,7,0) -> Concierge Overtime | K11: Front Desk | L11: =+VLOOKUP($A11,IncomeStatement!$A:$F,6,0) -> 252.4
A12: 60200R | B12: 2772.58 | C12: 2184 | D12: 0 | E12: 0 | F12: 4956.58 | G12: 0 | H12: =+B12+C12 -> 4956.58 | I12: =+VLOOKUP(A12,[1]Final!$A:$E,5,0) -> Concierge | J12: =+VLOOKUP(A12,[1]Final!$A:$G,7,0) -> Concierge Regular Pay | K12: Front Desk | L12: =+VLOOKUP($A12,IncomeStatement!$A:$F,6,0) -> #N/A
A13: 60300R | B13: 3056.37 | C13: 3500.68 | D13: 0 | E13: 0 | F13: 6557.05 | G13: 0 | H13: =+B13+C13 -> 6557.05 | I13: =+VLOOKUP(A13,[1]Final!$A:$E,5,0) -> Executive Housekeeper | J13: =+VLOOKUP(A13,[1]Final!$A:$G,7,0) -> Executive Housekeeper Regular Pay | K13: Management | L13: =+VLOOKUP($A13,IncomeStatement!$A:$F,6,0) -> #N/A
A14: 60350OT | C14: 375.13 | E14: 0 | F14: 375.13 | G14: 0 | H14: =+B14+C14 -> 375.13 | I14: =+VLOOKUP(A14,[1]Final!$A:$E,5,0) -> Housekeeping | J14: =+VLOOKUP(A14,[1]Final!$A:$G,7,0) -> Room Attendants Overtime | K14: Housekeeping | L14: =+VLOOKUP($A14,IncomeStatement!$A:$F,6,0) -> 375.82
A15: 60350R | B15: 25397.15 | C15: 26913.36 | D15: 0 | E15: 0 | F15: 52310.51 | G15: 0 | H15: =+B15+C15 -> 52310.51 | I15: =+VLOOKUP(A15,[1]Final!$A:$E,5,0) -> Housekeeping | J15: =+VLOOKUP(A15,[1]Final!$A:$G,7,0) -> Room Attendants Regular Pay | K15: Housekeeping | L15: =+VLOOKUP($A15,IncomeStatement!$A:$F,6,0) -> #N/A
A16: 60390R | B16: 5080.13 | C16: 5441.08 | D16: 0 | E16: 0 | F16: 10521.21 | G16: 0 | H16: =+B16+C16 -> 10521.21 | I16: =+VLOOKUP(A16,[1]Final!$A:$E,5,0) -> Housekeeping Inspector | J16: =+VLOOKUP(A16,[1]Final!$A:$G,7,0) -> Inspectors Regular Pay | K16: Housekeeping | L16: =+VLOOKUP($A16,IncomeStatement!$A:$F,6,0) -> #N/A
A17: 60500R | C17: 113.62 | E17: 0 | F17: 113.62 | G17: 0 | H17: =+B17+C17 -> 113.62 | I17: =+VLOOKUP(A17,[1]Final!$A:$E,5,0) -> Laundry | J17: =+VLOOKUP(A17,[1]Final!$A:$G,7,0) -> Laundry Persons Regular Pay | K17: Laundry | L17: =+VLOOKUP($A17,IncomeStatement!$A:$F,6,0) -> #N/A
A18: 60650R | B18: 5728.92 | C18: 5585.62 | D18: 0 | E18: 0 | F18: 11314.54 | G18: 0 | H18: =+B18+C18 -> 11314.54 | I18: =+VLOOKUP(A18,[1]Final!$A:$E,5,0) -> House Person | J18: =+VLOOKUP(A18,[1]Final!$A:$G,7,0) -> House Persons Regular Pay | K18: Housekeeping | L18: =+VLOOKUP($A18,IncomeStatement!$A:$F,6,0) -> #N/A
A19: 62000R | B19: 4016.16 | C19: 4600 | D19: 0 | E19: 0 | F19: 8616.16 | G19: 0 | H19: =+B19+C19 -> 8616.16 | I19: =+VLOOKUP(A19,[1]Final!$A:$E,5,0) -> F&B Management | J19: =+VLOOKUP(A19,[1]Final!$A:$G,7,0) -> Food & Beverage Manager Regular Pay | K19: Service | L19: =+VLOOKUP($A19,IncomeStatement!$A:$F,6,0) -> #N/A
A20: 62050R | B20: 3143.08 | C20: 3600 | D20: 0 | E20: 0 | F20: 6743.08 | G20: 0 | H20: =+B20+C20 -> 6743.08 | I20: =+VLOOKUP(A20,[1]Final!$A:$E,5,0) -> Executive Chef | J20: =+VLOOKUP(A20,[1]Final!$A:$G,7,0) -> Executive Chef Regular Pay | K20: Kitchen | L20: =+VLOOKUP($A20,IncomeStatement!$A:$F,6,0) -> #N/A
A21: 62110R | B21: 2845.39 | C21: 3161.54 | D21: 0 | E21: 0 | F21: 6006.93 | G21: 0 | H21: =+B21+C21 -> 6006.93 | I21: =+VLOOKUP(A21,[1]Final!$A:$E,5,0) -> Food Outlet Management | J21: =+VLOOKUP(A21,[1]Final!$A:$G,7,0) -> Service Manager Regular Pay | K21: Service | L21: =+VLOOKUP($A21,IncomeStatement!$A:$F,6,0) -> #N/A
A22: 62230R | B22: 281.81 | C22: 511.53 | D22: 0 | E22: 0 | F22: 793.34 | G22: 0 | H22: =+B22+C22 -> 793.34 | I22: Banquet Server | J22: Banquet Other Wages Regular Pay | K22: Banquet and Catering | L22: =+VLOOKUP($A22,IncomeStatement!$A:$F,6,0) -> #N/A
A23: 62260R | B23: 5902.21 | C23: 5397.11 | D23: 0 | E23: 0 | F23: 11299.32 | G23: 0 | H23: =+B23+C23 -> 11299.32 | I23: =+VLOOKUP(A23,[1]Final!$A:$E,5,0) -> Banquet Server | J23: =+VLOOKUP(A23,[1]Final!$A:$G,7,0) -> Food Service Regular Pay | K23: Restaurant and Room Service | L23: =+VLOOKUP($A23,IncomeStatement!$A:$F,6,0) -> #N/A
A24: 62300R | B24: 1117.66 | C24: 1406.27 | D24: 0 | E24: 0 | F24: 2523.93 | G24: 0 | H24: =+B24+C24 -> 2523.93 | I24: =+VLOOKUP(A24,[1]Final!$A:$E,5,0) -> Host | J24: =+VLOOKUP(A24,[1]Final!$A:$G,7,0) -> Host Persons Regular Pay | K24: Restaurant and Room Service | L24: =+VLOOKUP($A24,IncomeStatement!$A:$F,6,0) -> #N/A
A25: 62500OT | B25: 14.25 | C25: 96.97 | D25: 0 | E25: 0 | F25: 111.22 | G25: 0 | H25: =+B25+C25 -> 111.22 | I25: =+VLOOKUP(A25,[1]Final!$A:$E,5,0) -> Culinary | J25: =+VLOOKUP(A25,[1]Final!$A:$G,7,0) -> Food Production Overtime | K25: Kitchen | L25: =+VLOOKUP($A25,IncomeStatement!$A:$F,6,0) -> 137.5
A26: 62500R | B26: 9141.41 | C26: 8329.52 | D26: 0 | E26: 0 | F26: 17470.93 | G26: 0 | H26: =+B26+C26 -> 17470.93 | I26: =+VLOOKUP(A26,[1]Final!$A:$E,5,0) -> Culinary | J26: =+VLOOKUP(A26,[1]Final!$A:$G,7,0) -> Food Production Regular Pay | K26: Kitchen | L26: =+VLOOKUP($A26,IncomeStatement!$A:$F,6,0) -> #N/A
A27: 62600R | B27: 2828.66 | C27: 2948.07 | D27: 0 | E27: 0 | F27: 5776.73 | G27: 0 | H27: =+B27+C27 -> 5776.73 | I27: =+VLOOKUP(A27,[1]Final!$A:$E,5,0) -> Kitchen Steward | J27: =+VLOOKUP(A27,[1]Final!$A:$G,7,0) -> Utility Persons Regular Pay | K27: Kitchen | L27: =+VLOOKUP($A27,IncomeStatement!$A:$F,6,0) -> #N/A
A28: 64100R | B28: 6238.39 | C28: 5474.11 | D28: 0 | E28: 0 | F28: 11712.5 | G28: 0 | H28: =+B28+C28 -> 11712.5 | I28: =+VLOOKUP(A28,[1]Final!$A:$E,5,0) -> Bartender Restaurant | J28: =+VLOOKUP(A28,[1]Final!$A:$G,7,0) -> Bartender Regular Pay | K28: Restaurant and Room Service | L28: =+VLOOKUP($A28,IncomeStatement!$A:$F,6,0) -> #N/A
A29: 73000R | B29: 5051.53 | C29: 6424.64 | D29: 0 | E29: 0 | F29: 11476.17 | G29: 0 | H29: =+B29+C29 -> 11476.17 | I29: =+VLOOKUP(A29,[1]Final!$A:$E,5,0) -> General Manager | J29: =+VLOOKUP(A29,[1]Final!$A:$G,7,0) -> General Manager Regular Pay | K29: A&G Management | L29: =+VLOOKUP($A29,IncomeStatement!$A:$F,6,0) -> #N/A
A30: 73400R | B30: 1356.74 | C30: 3459.69 | D30: 0 | E30: 0 | F30: 4816.43 | G30: 0 | H30: =+B30+C30 -> 4816.43 | I30: =+VLOOKUP(A30,[1]Final!$A:$E,5,0) -> Human Resource Manager | J30: =+VLOOKUP(A30,[1]Final!$A:$G,7,0) -> Human Resource Manager Regular Pay | K30: A&G Management | L30: =+VLOOKUP($A30,IncomeStatement!$A:$F,6,0) -> #N/A
A31: 73500R | B31: 7270.98 | C31: 8699.64 | D31: 0 | E31: 0 | F31: 15970.62 | G31: 0 | H31: =+B31+C31 -> 15970.62 | I31: =+VLOOKUP(A31,[1]Final!$A:$E,5,0) -> Accounting | J31: =+VLOOKUP(A31,[1]Final!$A:$G,7,0) -> Accounting Regular Pay | K31: A&G Non-Management | L31: =+VLOOKUP($A31,IncomeStatement!$A:$F,6,0) -> #N/A
A32: 75010R | B32: 1557.69 | C32: 5192.31 | D32: 0 | E32: 0 | F32: 6750 | G32: 0 | H32: =+B32+C32 -> 6750 | I32: =+VLOOKUP(A32,[1]Final!$A:$E,5,0) -> Sales and Marketing | J32: =+VLOOKUP(A32,[1]Final!$A:$G,7,0) -> Director of Sales Regular Pay | K32: Sales And Marketing Management | L32: =+VLOOKUP($A32,IncomeStatement!$A:$F,6,0) -> #N/A
A33: 75020R | B33: 3115.39 | C33: 3461.54 | D33: 0 | E33: 0 | F33: 6576.93 | G33: 0 | H33: =+B33+C33 -> 6576.93 | I33: =+VLOOKUP(A33,[1]Final!$A:$E,5,0) -> Sales Manager | J33: =+VLOOKUP(A33,[1]Final!$A:$G,7,0) -> Sales Manager Regular Pay | K33: Sales And Marketing Management | L33: =+VLOOKUP($A33,IncomeStatement!$A:$F,6,0) -> #N/A
A34: 75500OT | B34: 2.03 | C34: 6.32 | D34: 0 | E34: 0 | F34: 8.35 | G34: 0 | H34: =+B34+C34 -> 8.35 | I34: =+VLOOKUP(A34,[1]Final!$A:$E,5,0) -> Sales Administrative | J34: =+VLOOKUP(A34,[1]Final!$A:$G,7,0) -> Sales Admin Assistant Overtime | K34: Sales And Marketing Non-Management | L34: =+VLOOKUP($A34,IncomeStatement!$A:$F,6,0) -> 36.3
... A37: 77100R | B37: 3182.35 | C37: 2143.71 | D37: 0 | E37: 0 | F37: 5326.06 | G37: 0 | H37: =+B37+C37 -> 5326.06 | I37: =+VLOOKUP(A37,[1]Final!$A:$E,5,0) -> Maintenance | J37: =+VLOOKUP(A37,[1]Final!$A:$G,7,0) -> Maintenance Technicians Regular Pay | K37: Property Operation And Maintenance Non-Management | L37: =+VLOOKUP($A37,IncomeStatement!$A:$F,6,0) -> #N/A
A38: Grand Total | B38: 126138.92 | C38: 137067.12 | D38: 0 | E38: 0 | F38: 263206.04 | G38: 0

Sheet Mapping
A1: Hotel Name | B1: Income Statement Name | C1: GL Account # | D1: ADP Dept Code | E1: GL Account Name | F1: Payroll Register Name
A2: The Sound Hotel Seattle Belltown, Tapestry Collection by Hilton | B2: A&G Management | C2: 73000R | D2: 730000 | E2: General Manager Regular Pay | F2: General Manager
A3: The Sound Hotel Seattle Belltown, Tapestry Collection by Hilton | B3: A&G Management | C3: 73400R | D3: 734000 | E3: Human Resource Manager Regular Pay | F3: Human Resource Manager
A4: The Sound Hotel Seattle Belltown, Tapestry Collection by Hilton | B4: A&G Non-Management | C4: 73500R | D4: 735000 | E4: Accounting Regular Pay | F4: Accounting
A5: The Sound Hotel Seattle Belltown, Tapestry Collection by Hilton | B5: Banquet and Catering | C5: 62230R | D5: 622300 | E5: Banquet Other Wages Regular Pay | F5: Banquet Server
A6: The Sound Hotel Seattle Belltown, Tapestry Collection by Hilton | B6: Front Desk | C6: 60000OT | D6: 600000 | E6: Night Auditor Overtime | F6: Night Audit
A7: The Sound Hotel Seattle Belltown, Tapestry Collection by Hilton | B7: Front Desk | C7: 60000R | D7: 600000 | E7: Night Auditor Regular Pay | F7: Night Audit
A8: The Sound Hotel Seattle Belltown, Tapestry Collection by Hilton | B8: Front Desk | C8: 60200OT | D8: 602000 | E8: Concierge Overtime | F8: Concierge
A9: The Sound Hotel Seattle Belltown, Tapestry Collection by Hilton | B9: Front Desk | C9: 60200R | D9: 602000 | E9: Concierge Regular Pay | F9: Concierge
A10: The Sound Hotel Seattle Belltown, Tapestry Collection by Hilton | B10: Guest Services | C10: 60040OT | D10: 600400 | E10: Guest Service Supervisor Overtime | F10: Guest Service Supervisor
A11: The Sound Hotel Seattle Belltown, Tapestry Collection by Hilton | B11: Guest Services | C11: 60040R | D11: 600400 | E11: Guest Service Supervisor Regular Pay | F11: Guest Service Supervisor
A12: The Sound Hotel Seattle Belltown, Tapestry Collection by Hilton | B12: Guest Services | C12: 60050R | D12: 600500 | E12: Guest Service Representatives Regular Pay | F12: Guest Service Representatives
A13: The Sound Hotel Seattle Belltown, Tapestry Collection by Hilton | B13: Housekeeping | C13: 60350OT | D13: 603500 | E13: Room Attendants Overtime | F13: Housekeeping
... A35: The Sound Hotel Seattle Belltown, Tapestry Collection by Hilton | B35: Service | C35: 62110R | D35: 621100 | E35: Service Manager Regular Pay | F35: Food Outlet Management

Sheet Jul Payroll
A1: External ID | B1: Transaction Date | C1: Posting Period | D1: Memo | E1: Subsidiary | F1: GL Account Number | G1: GL Account Name | H1: Debit | I1: Credit | J1: Memo (Line) | K1: Outlet | L1: Location
A2: THG-00059 | B2: 46207 | D2: Payroll Period 06.21.2026 to 07.04.2026 # PD 07.09.2026 | E2: 474 | F2: 21500 | H2: 0 | I2: 2205.23 | J2: ADP Garnishment Liability - Payroll Period 06.21.2026 to 07.04.2026 # PD 07.09.2026
A3: THG-00059 | B3: 46207 | D3: Payroll Period 06.21.2026 to 07.04.2026 # PD 07.09.2026 | E3: 474 | F3: 21500 | H3: 0 | I3: 118391.41 | J3: ADP Wagepay - Payroll Period 06.21.2026 to 07.04.2026 # PD 07.09.2026
A4: THG-00059 | B4: 46207 | D4: Payroll Period 06.21.2026 to 07.04.2026 # PD 07.09.2026 | E4: 474 | F4: 21500 | H4: 0 | I4: 3282.72 | J4: Employee Benefits Contributions - Payroll Period 06.21.2026 to 07.04.2026 # PD 07.09.2026
A5: THG-00059 | B5: 46207 | D5: Payroll Period 06.21.2026 to 07.04.2026 # PD 07.09.2026 | E5: 474 | F5: 21500 | H5: 0 | I5: 27537.21 | J5: Employee Tax Liability - Payroll Period 06.21.2026 to 07.04.2026 # PD 07.09.2026
A6: THG-00059 | B6: 46207 | D6: Payroll Period 06.21.2026 to 07.04.2026 # PD 07.09.2026 | E6: 474 | F6: 21500 | H6: 0 | I6: 12846.47 | J6: Employer Benefits Cost - Payroll Period 06.21.2026 to 07.04.2026 # PD 07.09.2026
A7: THG-00059 | B7: 46207 | D7: Payroll Period 06.21.2026 to 07.04.2026 # PD 07.09.2026 | E7: 474 | F7: 21500 | H7: 0 | I7: 13179.28 | J7: Employer Tax Liability - Payroll Period 06.21.2026 to 07.04.2026 # PD 07.09.2026
A8: THG-00059 | B8: 46207 | D8: Payroll Period 06.21.2026 to 07.04.2026 # PD 07.09.2026 | E8: 474 | F8: 22052 | H8: 10952.44 | I8: 0 | J8: Charge Tips Paid - Payroll Period 06.21.2026 to 07.04.2026 # PD 07.09.2026
A9: THG-00059 | B9: 46207 | D9: Payroll Period 06.21.2026 to 07.04.2026 # PD 07.09.2026 | E9: 474 | F9: 22060 | H9: 0 | I9: 7355.27 | J9: ADP Retirement Liability - Payroll Period 06.21.2026 to 07.04.2026 # PD 07.09.2026
A10: THG-00059 | B10: 46207 | D10: Payroll Period 06.21.2026 to 07.04.2026 # PD 07.09.2026 | E10: 474 | F10: 51920 | H10: 875 | I10: 0 | J10: Reimbursements - Payroll Period 06.21.2026 to 07.04.2026 # PD 07.09.2026
A11: THG-00059 | B11: 46207 | D11: Payroll Period 06.21.2026 to 07.04.2026 # PD 07.09.2026 | E11: 474 | F11: 60700 | H11: 941.48 | I11: 0 | J11: Bonus and Incentive - Rooms - Payroll Period 06.21.2026 to 07.04.2026 # PD 07.09.2026
A12: THG-00059 | B12: 46207 | D12: Payroll Period 06.21.2026 to 07.04.2026 # PD 07.09.2026 | E12: 474 | F12: 60920 | H12: 5695.68 | I12: 0 | J12: Rooms Employer Tax - Payroll Period 06.21.2026 to 07.04.2026 # PD 07.09.2026
A13: THG-00059 | B13: 46207 | D13: Payroll Period 06.21.2026 to 07.04.2026 # PD 07.09.2026 | E13: 474 | F13: 60920 | H13: 7.02 | I13: 0 | J13: Rooms Employer Tax - Payroll Period 06.21.2026 to 07.04.2026 # PD 07.09.2026
... A18: THG-00059 | B18: 46207 | D18: Payroll Period 06.21.2026 to 07.04.2026 # PD 07.09.2026 | E18: 474 | F18: 61950 | H18: 0 | I18: 29.09 | J18: Uniforms - Payroll Period 06.21.2026 to 07.04.2026 # PD 07.09.2026
A19: THG-00059 | B19: 46207 | D19: Payroll Period 06.21.2026 to 07.04.2026 # PD 07.09.2026 | E19: 474 | F19: 62700 | H19: 10.82 | I19: 0 | J19: Bonus and Incentive - Payroll Period 06.21.2026 to 07.04.2026 # PD 07.09.2026 | K19: 01 Restaurant 1
A20: THG-00059 | B20: 46207 | D20: Payroll Period 06.21.2026 to 07.04.2026 # PD 07.09.2026 | E20: 474 | F20: 62920 | H20: 3671.32 | I20: 0 | J20: F&B Employer Tax - Payroll Period 06.21.2026 to 07.04.2026 # PD 07.09.2026 | K20: 01 Restaurant 1
A21: THG-00059 | B21: 46207 | D21: Payroll Period 06.21.2026 to 07.04.2026 # PD 07.09.2026 | E21: 474 | F21: 62920 | H21: 100.28 | I21: 0 | J21: F&B Employer Tax - Payroll Period 06.21.2026 to 07.04.2026 # PD 07.09.2026 | K21: 11 Banquets
A22: THG-00059 | B22: 46207 | D22: Payroll Period 06.21.2026 to 07.04.2026 # PD 07.09.2026 | E22: 474 | F22: 62940 | H22: 3614.3 | I22: 0 | J22: Employer Benefits Cost - Payroll Period 06.21.2026 to 07.04.2026 # PD 07.09.2026 | K22: 01 Restaurant 1
A23: THG-00059 | B23: 46207 | D23: Payroll Period 06.21.2026 to 07.04.2026 # PD 07.09.2026 | E23: 474 | F23: 62940 | H23: 423.24 | I23: 0 | J23: Employer Match Retirement - Payroll Period 06.21.2026 to 07.04.2026 # PD 07.09.2026 | K23: 01 Restaurant 1
A24: THG-00059 | B24: 46207 | D24: Payroll Period 06.21.2026 to 07.04.2026 # PD 07.09.2026 | E24: 474 | F24: 62990 | H24: 3100.5 | I24: 0 | J24: Supplemental Pay - Payroll Period 06.21.2026 to 07.04.2026 # PD 07.09.2026 | K24: 01 Restaurant 1
A25: THG-00059 | B25: 46207 | D25: Payroll Period 06.21.2026 to 07.04.2026 # PD 07.09.2026 | E25: 474 | F25: 63905 | H25: 1428.08 | I25: 0 | J25: Service Charges - Payroll Period 06.21.2026 to 07.04.2026 # PD 07.09.2026 | K25: 01 Restaurant 1
A26: THG-00059 | B26: 46207 | D26: Payroll Period 06.21.2026 to 07.04.2026 # PD 07.09.2026 | E26: 474 | F26: 63905 | H26: 803.14 | I26: 0 | J26: Service Charges - Payroll Period 06.21.2026 to 07.04.2026 # PD 07.09.2026 | K26: 11 Banquets
A27: THG-00059 | B27: 46207 | D27: Payroll Period 06.21.2026 to 07.04.2026 # PD 07.09.2026 | E27: 474 | F27: 64905 | H27: 171.7 | I27: 0 | J27: Service Charges - Payroll Period 06.21.2026 to 07.04.2026 # PD 07.09.2026 | K27: 01 Restaurant 1
A28: THG-00059 | B28: 46207 | D28: Payroll Period 06.21.2026 to 07.04.2026 # PD 07.09.2026 | E28: 474 | F28: 64920 | H28: 649.83 | I28: 0 | J28: Bar Employer Tax - Payroll Period 06.21.2026 to 07.04.2026 # PD 07.09.2026 | K28: 01 Restaurant 1
A29: THG-00059 | B29: 46207 | D29: Payroll Period 06.21.2026 to 07.04.2026 # PD 07.09.2026 | E29: 474 | F29: 64990 | H29: 173.84 | I29: 0 | J29: Supplemental Pay - Payroll Period 06.21.2026 to 07.04.2026 # PD 07.09.2026 | K29: 01 Restaurant 1
A30: THG-00059 | B30: 46207 | D30: Payroll Period 06.21.2026 to 07.04.2026 # PD 07.09.2026 | E30: 474 | F30: 73920 | H30: 1462.64 | I30: 0 | J30: A&G Employer Tax - Payroll Period 06.21.2026 to 07.04.2026 # PD 07.09.2026
A31: THG-00059 | B31: 46207 | D31: Payroll Period 06.21.2026 to 07.04.2026 # PD 07.09.2026 | E31: 474 | F31: 73940 | H31: 1708.4 | I31: 0 | J31: Employer Benefits Cost - Payroll Period 06.21.2026 to 07.04.2026 # PD 07.09.2026
A32: THG-00059 | B32: 46207 | D32: Payroll Period 06.21.2026 to 07.04.2026 # PD 07.09.2026 | E32: 474 | F32: 73940 | H32: 626.34 | I32: 0 | J32: Employer Match Retirement - Payroll Period 06.21.2026 to 07.04.2026 # PD 07.09.2026
A33: THG-00059 | B33: 46207 | D33: Payroll Period 06.21.2026 to 07.04.2026 # PD 07.09.2026 | E33: 474 | F33: 73990 | H33: 4548.39 | I33: 0 | J33: Supplemental Pay - Payroll Period 06.21.2026 to 07.04.2026 # PD 07.09.2026
A34: THG-00059 | B34: 46207 | D34: Payroll Period 06.21.2026 to 07.04.2026 # PD 07.09.2026 | E34: 474 | F34: 75920 | H34: 932.38 | I34: 0 | J34: Sales Employer Tax - Payroll Period 06.21.2026 to 07.04.2026 # PD 07.09.2026
A35: THG-00059 | B35: 46207 | D35: Payroll Period 06.21.2026 to 07.04.2026 # PD 07.09.2026 | E35: 474 | F35: 75940 | H35: 1016.35 | I35: 0 | J35: Employer Benefits Cost - Payroll Period 06.21.2026 to 07.04.2026 # PD 07.09.2026
A36: THG-00059 | B36: 46207 | D36: Payroll Period 06.21.2026 to 07.04.2026 # PD 07.09.2026 | E36: 474 | F36: 75990 | H36: 3980.77 | I36: 0 | J36: Supplemental Pay - Payroll Period 06.21.2026 to 07.04.2026 # PD 07.09.2026
A37: THG-00059 | B37: 46207 | D37: Payroll Period 06.21.2026 to 07.04.2026 # PD 07.09.2026 | E37: 474 | F37: 77940 | H37: 659.41 | I37: 0 | J37: Maint Employer Tax - Payroll Period 06.21.2026 to 07.04.2026 # PD 07.09.2026
A38: THG-00059 | B38: 46207 | D38: Payroll Period 06.21.2026 to 07.04.2026 # PD 07.09.2026 | E38: 474 | F38: 77960 | H38: 606.04 | I38: 0 | J38: Employer Benefits Cost - Payroll Period 06.21.2026 to 07.04.2026 # PD 07.09.2026
A39: THG-00059 | B39: 46207 | D39: Payroll Period 06.21.2026 to 07.04.2026 # PD 07.09.2026 | E39: 474 | F39: 77960 | H39: 130.35 | I39: 0 | J39: Employer Match Retirement - Payroll Period 06.21.2026 to 07.04.2026 # PD 07.09.2026
A40: THG-00059 | B40: 46207 | D40: Payroll Period 06.21.2026 to 07.04.2026 # PD 07.09.2026 | E40: 474 | F40: 78100 | H40: 1179.78 | I40: 0 | J40: Supplemental Pay - Payroll Period 06.21.2026 to 07.04.2026 # PD 07.09.2026
A41: THG-00059 | B41: 46207 | D41: Payroll Period 06.21.2026 to 07.04.2026 # PD 07.09.2026 | E41: 474 | F41: 60000OT | H41: 82.22 | I41: 0 | J41: Night Audit OT - Payroll Period 06.21.2026 to 07.04.2026 # PD 07.09.2026
A42: THG-00059 | B42: 46207 | D42: Payroll Period 06.21.2026 to 07.04.2026 # PD 07.09.2026 | E42: 474 | F42: 60000R | H42: 4558.08 | I42: 0 | J42: Night Audit Wages - Payroll Period 06.21.2026 to 07.04.2026 # PD 07.09.2026
A43: THG-00059 | B43: 46207 | D43: Payroll Period 06.21.2026 to 07.04.2026 # PD 07.09.2026 | E43: 474 | F43: 60010R | H43: 2624.51 | I43: 0 | J43: Guest Service Mgr Wages - Payroll Period 06.21.2026 to 07.04.2026 # PD 07.09.2026
A44: THG-00059 | B44: 46207 | D44: Payroll Period 06.21.2026 to 07.04.2026 # PD 07.09.2026 | E44: 474 | F44: 60020R | H44: 3824.62 | I44: 0 | J44: Asst General Manager Wages - Payroll Period 06.21.2026 to 07.04.2026 # PD 07.09.2026
A45: THG-00059 | B45: 46207 | D45: Payroll Period 06.21.2026 to 07.04.2026 # PD 07.09.2026 | E45: 474 | F45: 60040OT | H45: 0.87 | I45: 0 | J45: Guest Svc Super OT - Payroll Period 06.21.2026 to 07.04.2026 # PD 07.09.2026
A46: THG-00059 | B46: 46207 | D46: Payroll Period 06.21.2026 to 07.04.2026 # PD 07.09.2026 | E46: 474 | F46: 60040R | H46: 2673.13 | I46: 0 | J46: Guest Service Super Wages - Payroll Period 06.21.2026 to 07.04.2026 # PD 07.09.2026
A47: THG-00059 | B47: 46207 | D47: Payroll Period 06.21.2026 to 07.04.2026 # PD 07.09.2026 | E47: 474 | F47: 60050R | H47: 7748.01 | I47: 0 | J47: Guest Service Wages - Payroll Period 06.21.2026 to 07.04.2026 # PD 07.09.2026
A48: THG-00059 | B48: 46207 | D48: Payroll Period 06.21.2026 to 07.04.2026 # PD 07.09.2026 | E48: 474 | F48: 60200R | H48: 2772.58 | I48: 0 | J48: Concierge Wages - Payroll Period 06.21.2026 to 07.04.2026 # PD 07.09.2026
A49: THG-00059 | B49: 46207 | D49: Payroll Period 06.21.2026 to 07.04.2026 # PD 07.09.2026 | E49: 474 | F49: 60300R | H49: 3056.37 | I49: 0 | J49: Exec Housekeeper Wages - Payroll Period 06.21.2026 to 07.04.2026 # PD 07.09.2026
A50: THG-00059 | B50: 46207 | D50: Payroll Period 06.21.2026 to 07.04.2026 # PD 07.09.2026 | E50: 474 | F50: 60350R | H50: 25397.15 | I50: 0 | J50: Room Attendant Wages - Payroll Period 06.21.2026 to 07.04.2026 # PD 07.09.2026
A51: THG-00059 | B51: 46207 | D51: Payroll Period 06.21.2026 to 07.04.2026 # PD 07.09.2026 | E51: 474 | F51: 60390R | H51: 5080.13 | I51: 0 | J51: Inspector Wages - Payroll Period 06.21.2026 to 07.04.2026 # PD 07.09.2026
A52: THG-00059 | B52: 46207 | D52: Payroll Period 06.21.2026 to 07.04.2026 # PD 07.09.2026 | E52: 474 | F52: 60650R | H52: 5728.92 | I52: 0 | J52: Houseperson Wages - Payroll Period 06.21.2026 to 07.04.2026 # PD 07.09.2026
A53: THG-00059 | B53: 46207 | D53: Payroll Period 06.21.2026 to 07.04.2026 # PD 07.09.2026 | E53: 474 | F53: 62000R | H53: 4016.16 | I53: 0 | J53: F&B Manager Wages - Payroll Period 06.21.2026 to 07.04.2026 # PD 07.09.2026 | K53: 01 Restaurant 1
A54: THG-00059 | B54: 46207 | D54: Payroll Period 06.21.2026 to 07.04.2026 # PD 07.09.2026 | E54: 474 | F54: 62050R | H54: 3143.08 | I54: 0 | J54: Exec Chef Wages - Payroll Period 06.21.2026 to 07.04.2026 # PD 07.09.2026 | K54: 01 Restaurant 1
A55: THG-00059 | B55: 46207 | D55: Payroll Period 06.21.2026 to 07.04.2026 # PD 07.09.2026 | E55: 474 | F55: 62110R | H55: 2845.39 | I55: 0 | J55: Restaurant Manager Wages - Payroll Period 06.21.2026 to 07.04.2026 # PD 07.09.2026 | K55: 01 Restaurant 1
A56: THG-00059 | B56: 46207 | D56: Payroll Period 06.21.2026 to 07.04.2026 # PD 07.09.2026 | E56: 474 | F56: 62230R | H56: 281.81 | I56: 0 | J56: Banq Server Wages - Payroll Period 06.21.2026 to 07.04.2026 # PD 07.09.2026 | K56: 11 Banquets
A57: THG-00059 | B57: 46207 | D57: Payroll Period 06.21.2026 to 07.04.2026 # PD 07.09.2026 | E57: 474 | F57: 62260R | H57: 5902.21 | I57: 0 | J57: Server Wages - Payroll Period 06.21.2026 to 07.04.2026 # PD 07.09.2026 | K57: 01 Restaurant 1
A58: THG-00059 | B58: 46207 | D58: Payroll Period 06.21.2026 to 07.04.2026 # PD 07.09.2026 | E58: 474 | F58: 62300R | H58: 1117.66 | I58: 0 | J58: Host Person Wages - Payroll Period 06.21.2026 to 07.04.2026 # PD 07.09.2026 | K58: 01 Restaurant 1
A59: THG-00059 | B59: 46207 | D59: Payroll Period 06.21.2026 to 07.04.2026 # PD 07.09.2026 | E59: 474 | F59: 62500OT | H59: 14.25 | I59: 0 | J59: Line Cook OT - Payroll Period 06.21.2026 to 07.04.2026 # PD 07.09.2026 | K59: 01 Restaurant 1
A60: THG-00059 | B60: 46207 | D60: Payroll Period 06.21.2026 to 07.04.2026 # PD 07.09.2026 | E60: 474 | F60: 62500R | H60: 9141.41 | I60: 0 | J60: Line Cook Wages - Payroll Period 06.21.2026 to 07.04.2026 # PD 07.09.2026 | K60: 01 Restaurant 1
A61: THG-00059 | B61: 46207 | D61: Payroll Period 06.21.2026 to 07.04.2026 # PD 07.09.2026 | E61: 474 | F61: 62600R | H61: 2828.66 | I61: 0 | J61: Kitchen Utility Wages - Payroll Period 06.21.2026 to 07.04.2026 # PD 07.09.2026 | K61: 01 Restaurant 1
A62: THG-00059 | B62: 46207 | D62: Payroll Period 06.21.2026 to 07.04.2026 # PD 07.09.2026 | E62: 474 | F62: 64100R | H62: 6238.39 | I62: 0 | J62: Bartender Wages - Payroll Period 06.21.2026 to 07.04.2026 # PD 07.09.2026 | K62: 01 Restaurant 1
A63: THG-00059 | B63: 46207 | D63: Payroll Period 06.21.2026 to 07.04.2026 # PD 07.09.2026 | E63: 474 | F63: 73000R | H63: 5051.53 | I63: 0 | J63: GM Wages - Payroll Period 06.21.2026 to 07.04.2026 # PD 07.09.2026
A64: THG-00059 | B64: 46207 | D64: Payroll Period 06.21.2026 to 07.04.2026 # PD 07.09.2026 | E64: 474 | F64: 73400R | H64: 1356.74 | I64: 0 | J64: HR Wages - Payroll Period 06.21.2026 to 07.04.2026 # PD 07.09.2026
A65: THG-00059 | B65: 46207 | D65: Payroll Period 06.21.2026 to 07.04.2026 # PD 07.09.2026 | E65: 474 | F65: 73500R | H65: 7270.98 | I65: 0 | J65: Accounting Wages - Payroll Period 06.21.2026 to 07.04.2026 # PD 07.09.2026
A66: THG-00059 | B66: 46207 | D66: Payroll Period 06.21.2026 to 07.04.2026 # PD 07.09.2026 | E66: 474 | F66: 75010R | H66: 1557.69 | I66: 0 | J66: DOS Wages - Payroll Period 06.21.2026 to 07.04.2026 # PD 07.09.2026
A67: THG-00059 | B67: 46207 | D67: Payroll Period 06.21.2026 to 07.04.2026 # PD 07.09.2026 | E67: 474 | F67: 75020R | H67: 3115.39 | I67: 0 | J67: Sales Manager Wages - Payroll Period 06.21.2026 to 07.04.2026 # PD 07.09.2026
A68: THG-00059 | B68: 46207 | D68: Payroll Period 06.21.2026 to 07.04.2026 # PD 07.09.2026 | E68: 474 | F68: 75500OT | H68: 2.03 | I68: 0 | J68: Sales Admin OT - Payroll Period 06.21.2026 to 07.04.2026 # PD 07.09.2026
A69: THG-00059 | B69: 46207 | D69: Payroll Period 06.21.2026 to 07.04.2026 # PD 07.09.2026 | E69: 474 | F69: 75500R | H69: 2185.02 | I69: 0 | J69: Sales Administrative Wages - Payroll Period 06.21.2026 to 07.04.2026 # PD 07.09.2026
A70: THG-00059 | B70: 46207 | D70: Payroll Period 06.21.2026 to 07.04.2026 # PD 07.09.2026 | E70: 474 | F70: 77000R | H70: 3341.58 | I70: 0 | J70: Maintenance Chief Wages - Payroll Period 06.21.2026 to 07.04.2026 # PD 07.09.2026
A71: THG-00059 | B71: 46207 | D71: Payroll Period 06.21.2026 to 07.04.2026 # PD 07.09.2026 | E71: 474 | F71: 77100R | H71: 3182.35 | I71: 0 | J71: Maint Tech Wages - Payroll Period 06.21.2026 to 07.04.2026 # PD 07.09.2026
A72: THG-00059 | B72: 46221 | D72: Payroll Period 07.05.2026 to 07.18.2026 # PD 07.24.2026 | E72: 474 | F72: 21500 | H72: 0 | I72: 2205.23 | J72: ADP Garnishment Liability - Payroll Period 07.05.2026 to 07.18.2026
A73: THG-00059 | B73: 46221 | D73: Payroll Period 07.05.2026 to 07.18.2026 # PD 07.24.2026 | E73: 474 | F73: 21500 | H73: 0 | I73: 117166.11 | J73: ADP Wagepay - Payroll Period 07.05.2026 to 07.18.2026
A74: THG-00059 | B74: 46221 | D74: Payroll Period 07.05.2026 to 07.18.2026 # PD 07.24.2026 | E74: 474 | F74: 21500 | H74: 0 | I74: 3253.9 | J74: Employee Benefits Contributions - Payroll Period 07.05.2026 to 07.18.2026
A75: THG-00059 | B75: 46221 | D75: Payroll Period 07.05.2026 to 07.18.2026 # PD 07.24.2026 | E75: 474 | F75: 21500 | H75: 0 | I75: 28025.7 | J75: Employee Tax Liability - Payroll Period 07.05.2026 to 07.18.2026
A76: THG-00059 | B76: 46221 | D76: Payroll Period 07.05.2026 to 07.18.2026 # PD 07.24.2026 | E76: 474 | F76: 21500 | H76: 0 | I76: 12846.47 | J76: Employer Benefits Cost - Payroll Period 07.05.2026 to 07.18.2026
A77: THG-00059 | B77: 46221 | D77: Payroll Period 07.05.2026 to 07.18.2026 # PD 07.24.2026 | E77: 474 | F77: 21500 | H77: 0 | I77: 13184.35 | J77: Employer Tax Liability - Payroll Period 07.05.2026 to 07.18.2026
A78: THG-00059 | B78: 46221 | D78: Payroll Period 07.05.2026 to 07.18.2026 # PD 07.24.2026 | E78: 474 | F78: 22052 | H78: 10809.88 | I78: 0 | J78: Charge Tips Paid - Payroll Period 07.05.2026 to 07.18.2026
A79: THG-00059 | B79: 46221 | D79: Payroll Period 07.05.2026 to 07.18.2026 # PD 07.24.2026 | E79: 474 | F79: 22060 | H79: 0 | I79: 7374.08 | J79: ADP Retirement Liability - Payroll Period 07.05.2026 to 07.18.2026
A80: THG-00059 | B80: 46221 | D80: Payroll Period 07.05.2026 to 07.18.2026 # PD 07.24.2026 | E80: 474 | F80: 60700 | H80: 2730.94 | I80: 0 | J80: Bonus and Incentive - Rooms - Payroll Period 07.05.2026 to 07.18.2026
A81: THG-00059 | B81: 46221 | D81: Payroll Period 07.05.2026 to 07.18.2026 # PD 07.24.2026 | E81: 474 | F81: 60920 | H81: 32 | I81: 0 | J81: Rooms Employer Tax - Payroll Period 07.05.2026 to 07.18.2026
A82: THG-00059 | B82: 46221 | D82: Payroll Period 07.05.2026 to 07.18.2026 # PD 07.24.2026 | E82: 474 | F82: 60920 | H82: 5944.51 | I82: 0 | J82: Rooms Employer Tax - Payroll Period 07.05.2026 to 07.18.2026
A83: THG-00059 | B83: 46221 | D83: Payroll Period 07.05.2026 to 07.18.2026 # PD 07.24.2026 | E83: 474 | F83: 60940 | H83: 14.81 | I83: 0 | J83: Employer Match Retirement - Payroll Period 07.05.2026 to 07.18.2026
... A87: THG-00059 | B87: 46221 | D87: Payroll Period 07.05.2026 to 07.18.2026 # PD 07.24.2026 | E87: 474 | F87: 61950 | H87: 0 | I87: 19.34 | J87: Uniforms - Payroll Period 07.05.2026 to 07.18.2026
A88: THG-00059 | B88: 46221 | D88: Payroll Period 07.05.2026 to 07.18.2026 # PD 07.24.2026 | E88: 474 | F88: 62700 | H88: 140.66 | I88: 0 | J88: Bonus and Incentive - Payroll Period 07.05.2026 to 07.18.2026 | K88: 01 Restaurant 1
A89: THG-00059 | B89: 46221 | D89: Payroll Period 07.05.2026 to 07.18.2026 # PD 07.24.2026 | E89: 474 | F89: 62920 | H89: 3416.91 | I89: 0 | J89: F&B Employer Tax - Payroll Period 07.05.2026 to 07.18.2026 | K89: 01 Restaurant 1
A90: THG-00059 | B90: 46221 | D90: Payroll Period 07.05.2026 to 07.18.2026 # PD 07.24.2026 | E90: 474 | F90: 62920 | H90: 137.8 | I90: 0 | J90: F&B Employer Tax - Payroll Period 07.05.2026 to 07.18.2026 | K90: 11 Banquets
A91: THG-00059 | B91: 46221 | D91: Payroll Period 07.05.2026 to 07.18.2026 # PD 07.24.2026 | E91: 474 | F91: 62940 | H91: 3614.3 | I91: 0 | J91: Employer Benefits Cost - Payroll Period 07.05.2026 to 07.18.2026 | K91: 01 Restaurant 1
A92: THG-00059 | B92: 46221 | D92: Payroll Period 07.05.2026 to 07.18.2026 # PD 07.24.2026 | E92: 474 | F92: 62940 | H92: 364.8 | I92: 0 | J92: Employer Match Retirement - Payroll Period 07.05.2026 to 07.18.2026 | K92: 01 Restaurant 1
A93: THG-00059 | B93: 46221 | D93: Payroll Period 07.05.2026 to 07.18.2026 # PD 07.24.2026 | E93: 474 | F93: 62990 | H93: 244.87 | I93: 0 | J93: Supplemental Pay - Payroll Period 07.05.2026 to 07.18.2026 | K93: 01 Restaurant 1
A94: THG-00059 | B94: 46221 | D94: Payroll Period 07.05.2026 to 07.18.2026 # PD 07.24.2026 | E94: 474 | F94: 63905 | H94: 889.3 | I94: 0 | J94: Service Charges - Payroll Period 07.05.2026 to 07.18.2026 | K94: 01 Restaurant 1
A95: THG-00059 | B95: 46221 | D95: Payroll Period 07.05.2026 to 07.18.2026 # PD 07.24.2026 | E95: 474 | F95: 63905 | H95: 979.35 | I95: 0 | J95: Service Charges - Payroll Period 07.05.2026 to 07.18.2026 | K95: 11 Banquets
A96: THG-00059 | B96: 46221 | D96: Payroll Period 07.05.2026 to 07.18.2026 # PD 07.24.2026 | E96: 474 | F96: 64905 | H96: 128.1 | I96: 0 | J96: Service Charges - Payroll Period 07.05.2026 to 07.18.2026 | K96: 01 Restaurant 1
A97: THG-00059 | B97: 46221 | D97: Payroll Period 07.05.2026 to 07.18.2026 # PD 07.24.2026 | E97: 474 | F97: 64910 | H97: 300 | I97: 0 | J97: Bonus and Incentive - Payroll Period 07.05.2026 to 07.18.2026 | K97: 01 Restaurant 1
A98: THG-00059 | B98: 46221 | D98: Payroll Period 07.05.2026 to 07.18.2026 # PD 07.24.2026 | E98: 474 | F98: 64920 | H98: 588.65 | I98: 0 | J98: Bar Employer Tax - Payroll Period 07.05.2026 to 07.18.2026 | K98: 01 Restaurant 1
A99: THG-00059 | B99: 46221 | D99: Payroll Period 07.05.2026 to 07.18.2026 # PD 07.24.2026 | E99: 474 | F99: 64990 | H99: 521.52 | I99: 0 | J99: Supplemental Pay - Payroll Period 07.05.2026 to 07.18.2026 | K99: 01 Restaurant 1
A100: THG-00059 | B100: 46221 | D100: Payroll Period 07.05.2026 to 07.18.2026 # PD 07.24.2026 | E100: 474 | F100: 73920 | H100: 1491.98 | I100: 0 | J100: A&G Employer Tax - Payroll Period 07.05.2026 to 07.18.2026
A101: THG-00059 | B101: 46221 | D101: Payroll Period 07.05.2026 to 07.18.2026 # PD 07.24.2026 | E101: 474 | F101: 73940 | H101: 1708.4 | I101: 0 | J101: Employer Benefits Cost - Payroll Period 07.05.2026 to 07.18.2026
A102: THG-00059 | B102: 46221 | D102: Payroll Period 07.05.2026 to 07.18.2026 # PD 07.24.2026 | E102: 474 | F102: 73940 | H102: 639.57 | I102: 0 | J102: Employer Match Retirement - Payroll Period 07.05.2026 to 07.18.2026
A103: THG-00059 | B103: 46221 | D103: Payroll Period 07.05.2026 to 07.18.2026 # PD 07.24.2026 | E103: 474 | F103: 75920 | H103: 924.34 | I103: 0 | J103: Sales Employer Tax - Payroll Period 07.05.2026 to 07.18.2026
A104: THG-00059 | B104: 46221 | D104: Payroll Period 07.05.2026 to 07.18.2026 # PD 07.24.2026 | E104: 474 | F104: 75940 | H104: 1016.35 | I104: 0 | J104: Employer Benefits Cost - Payroll Period 07.05.2026 to 07.18.2026
A105: THG-00059 | B105: 46221 | D105: Payroll Period 07.05.2026 to 07.18.2026 # PD 07.24.2026 | E105: 474 | F105: 77940 | H105: 647.44 | I105: 0 | J105: Maint Employer Tax - Payroll Period 07.05.2026 to 07.18.2026
A106: THG-00059 | B106: 46221 | D106: Payroll Period 07.05.2026 to 07.18.2026 # PD 07.24.2026 | E106: 474 | F106: 77960 | H106: 606.04 | I106: 0 | J106: Employer Benefits Cost - Payroll Period 07.05.2026 to 07.18.2026
A107: THG-00059 | B107: 46221 | D107: Payroll Period 07.05.2026 to 07.18.2026 # PD 07.24.2026 | E107: 474 | F107: 77960 | H107: 133.95 | I107: 0 | J107: Employer Match Retirement - Payroll Period 07.05.2026 to 07.18.2026
...

Sheet Final
A1: NS Account | B1: GL Account | C1: F&B Outlet | D1: ADP Dept | E1: Department Title | F1: Division (Just for reference) | G1: NS Account Name
A2: 60000R | B2: 60000 | D2: 600000 | E2: Night Audit | F2: Rooms - Front Desk | G2: Night Auditor Regular Pay
A3: 60000OT | B3: 60000 | D3: 600000 | E3: Night Audit | F3: Rooms - Front Desk | G3: Night Auditor Overtime
A4: 60000R | B4: 60000 | D4: 600001 | E4: Night Audit Supervisor | F4: Rooms - Front Desk | G4: Night Auditor Regular Pay
A5: 60000OT | B5: 60000 | D5: 600001 | E5: Night Audit Supervisor | F5: Rooms - Front Desk | G5: Night Auditor Overtime
A6: 60010R | B6: 60010 | D6: 600100 | E6: Guest Service Management | F6: Rooms - Front Desk | G6: Guest Service Manager Regular Pay
A7: 60010OT | B7: 60010 | D7: 600100 | E7: Guest Service Management | F7: Rooms - Front Desk | G7: Guest Service Manager Overtime
A8: 60015R | B8: 60015 | D8: 600150 | E8: Asst. Guest Service Management | F8: Rooms - Front Desk | G8: Asst. Guest Service Manager Regular Pay
A9: 60015OT | B9: 60015 | D9: 600150 | E9: Asst. Guest Service Management | F9: Rooms - Front Desk | G9: Asst. Guest Service Manager Overtime
A10: 60020R | B10: 60020 | D10: 600200 | E10: Rooms Division Manager | F10: Rooms - Front Desk | G10: Rooms Division Manager Regular Pay
A11: 60020OT | B11: 60020 | D11: 600200 | E11: Rooms Division Manager | F11: Rooms - Front Desk | G11: Rooms Division Manager Overtime
A12: 60030R | B12: 60030 | D12: 600300 | E12: Asst. General Manager - RMS | F12: Rooms | G12: AGM - Rooms Regular Pay
A13: 60030OT | B13: 60030 | D13: 600300 | E13: Asst. General Manager - RMS | F13: Rooms | G13: AGM - Rooms Overtime
... A69: 60675OT | B69: 60675 | D69: 606750 | E69: PBX | F69: Rooms | G69: PBX Operator Overtime
A70: 62000R | B70: 62000 | C70: 00 F&B General | D70: 620000 | E70: F&B Management | F70: Food Management | G70: Food & Beverage Manager Regular Pay
A71: 62000OT | B71: 62000 | C71: 00 F&B General | D71: 620000 | E71: F&B Management | F71: Food Management | G71: Food & Beverage Manager Overtime
A72: 62000R | B72: 62000 | C72: 01 Restaurant 1 | D72: 620001 | E72: F&B Management | F72: Food Management | G72: Food & Beverage Manager Regular Pay
A73: 62000OT | B73: 62000 | C73: 01 Restaurant 1 | D73: 620001 | E73: F&B Management | F73: Food Management | G73: Food & Beverage Manager Overtime
A74: 62000R | B74: 62000 | C74: 06 Lounge 1 | D74: 620002 | E74: F&B Management Bar | F74: Food Management | G74: Food & Beverage Manager Regular Pay
A75: 62000OT | B75: 62000 | C75: 06 Lounge 1 | D75: 620002 | E75: F&B Management Bar | F75: Food Management | G75: Food & Beverage Manager Overtime
A76: 62000R | B76: 62000 | C76: 07 Lounge 2 | D76: 620003 | E76: F&B Management Bar | F76: Food Management | G76: Food & Beverage Manager Regular Pay
A77: 62000OT | B77: 62000 | C77: 07 Lounge 2 | D77: 620003 | E77: F&B Management Bar | F77: Food Management | G77: Food & Beverage Manager Overtime
A78: 62000R | B78: 62000 | C78: 02 Restaurant 2 | D78: 620020 | E78: F&B Management | F78: Food Management | G78: Food & Beverage Manager Regular Pay
A79: 62000OT | B79: 62000 | C79: 02 Restaurant 2 | D79: 620020 | E79: F&B Management | F79: Food Management | G79: Food & Beverage Manager Overtime
A80: 62000R | B80: 62000 | C80: 03 Restaurant 3 | D80: 620030 | E80: F&B Management | F80: Food Management | G80: Food & Beverage Manager Regular Pay
A81: 62000OT | B81: 62000 | C81: 03 Restaurant 3 | D81: 620030 | E81: F&B Management | F81: Food Management | G81: Food & Beverage Manager Overtime
... A249: 64120OT | B249: 64120 | C249: 08 Lounge 3 | D249: 627320 | E249: Bar Manager Restaurant | F249: Food - Bar | G249: Beverage Manager Overtime
A250: 64120R | B250: 64120 | D250: 627330 | E250: Bar Manager Restaurant | F250: Food - Bar | G250: Beverage Manager Regular Pay
A251: 64120OT | B251: 64120 | D251: 627330 | E251: Bar Manager Restaurant | F251: Food - Bar | G251: Beverage Manager Overtime
A252: 64120R | B252: 64120 | D252: 627340 | E252: Bar Manager Restaurant | F252: Food - Bar | G252: Beverage Manager Regular Pay
A253: 64120OT | B253: 64120 | D253: 627340 | E253: Bar Manager Restaurant | F253: Food - Bar | G253: Beverage Manager Overtime
A254: 62800R | B254: 62800 | C254: 01 Restaurant 1 | D254: 628000 | E254: F&B Training | F254: Food | G254: Training Payroll Regular Pay
A255: 62800OT | B255: 62800 | C255: 01 Restaurant 1 | D255: 628000 | E255: F&B Training | F255: Food | G255: Training Payroll Overtime
A256: 62800R | B256: 62800 | C256: 02 Restaurant 2 | D256: 628020 | E256: F&B Training | F256: Food | G256: Training Payroll Regular Pay
A257: 62800OT | B257: 62800 | C257: 02 Restaurant 2 | D257: 628020 | E257: F&B Training | F257: Food | G257: Training Payroll Overtime
A258: 62800R | B258: 62800 | C258: 03 Restaurant 3 | D258: 628030 | E258: F&B Training | F258: Food | G258: Training Payroll Regular Pay
A259: 62800OT | B259: 62800 | C259: 03 Restaurant 3 | D259: 628030 | E259: F&B Training | F259: Food | G259: Training Payroll Overtime
A260: 62800R | B260: 62800 | C260: 04 Restaurant 4 | D260: 628040 | E260: F&B Training | F260: Food | G260: Training Payroll Regular Pay
A261: 62800OT | B261: 62800 | C261: 04 Restaurant 4 | D261: 628040 | E261: F&B Training | F261: Food | G261: Training Payroll Overtime
A262: 62800R | B262: 62800 | C262: 05 Restaurant 5 | D262: 628050 | E262: F&B Training | F262: Food | G262: Training Payroll Regular Pay
A263: 62800OT | B263: 62800 | C263: 05 Restaurant 5 | D263: 628050 | E263: F&B Training | F263: Food | G263: Training Payroll Overtime
A264: 64100R | B264: 64100 | C264: 06 Lounge 1 | D264: 641000 | E264: Bartender | F264: Beverage | G264: Bartender Regular Pay
A265: 64100OT | B265: 64100 | C265: 06 Lounge 1 | D265: 641000 | E265: Bartender | F265: Beverage | G265: Bartender Overtime
... A283: 64120OT | B283: 64120 | C283: 08 Lounge 3 | D283: 641230 | E283: Bar Manager | F283: Beverage | G283: Beverage Manager Overtime
A284: 64120R | B284: 64120 | D284: 641240 | E284: Bar Manager | F284: Beverage | G284: Beverage Manager Regular Pay
A285: 64120OT | B285: 64120 | D285: 641240 | E285: Bar Manager | F285: Beverage | G285: Beverage Manager Overtime
A286: 64120R | B286: 64120 | D286: 641250 | E286: Bar Manager | F286: Beverage | G286: Beverage Manager Regular Pay
A287: 64120OT | B287: 64120 | D287: 641250 | E287: Bar Manager | F287: Beverage | G287: Beverage Manager Overtime
A288: 64150R | B288: 64150 | C288: 11 Banquets | D288: 641500 | E288: Banquet Bartender | F288: Banquets | G288: Banquet Bartender Regular Pay
A289: 64150OT | B289: 64150 | C289: 11 Banquets | D289: 641500 | E289: Banquet Bartender | F289: Banquets | G289: Banquet Bartender Overtime
A290: 64200R | B290: 64200 | C290: 06 Lounge 1 | D290: 642000 | E290: Cocktail Server | F290: Beverage | G290: Cocktail Servers Regular Pay
A291: 64200OT | B291: 64200 | C291: 06 Lounge 1 | D291: 642000 | E291: Cocktail Server | F291: Beverage | G291: Cocktail Servers Overtime
A292: 64200R | B292: 64200 | C292: 06 Lounge 1 | D292: 642001 | E292: Cocktail Server | F292: Beverage | G292: Cocktail Servers Regular Pay
A293: 64200OT | B293: 64200 | C293: 06 Lounge 1 | D293: 642001 | E293: Cocktail Server | F293: Beverage | G293: Cocktail Servers Overtime
A294: 64200R | B294: 64200 | C294: 07 Lounge 2 | D294: 642020 | E294: Cocktail Server | F294: Beverage | G294: Cocktail Servers Regular Pay
A295: 64200OT | B295: 64200 | C295: 07 Lounge 2 | D295: 642020 | E295: Cocktail Server | F295: Beverage | G295: Cocktail Servers Overtime
A296: 64200R | B296: 64200 | C296: 08 Lounge 3 | D296: 642030 | E296: Cocktail Server | F296: Beverage | G296: Cocktail Servers Regular Pay
A297: 64200OT | B297: 64200 | C297: 08 Lounge 3 | D297: 642030 | E297: Cocktail Server | F297: Beverage | G297: Cocktail Servers Overtime
A298: 64200R | B298: 64200 | D298: 642040 | E298: Cocktail Server | F298: Beverage | G298: Cocktail Servers Regular Pay
A299: 64200OT | B299: 64200 | D299: 642040 | E299: Cocktail Server | F299: Beverage | G299: Cocktail Servers Overtime
A300: 64200R | B300: 64200 | D300: 642050 | E300: Cocktail Server | F300: Beverage | G300: Cocktail Servers Regular Pay
A301: 64200OT | B301: 64200 | D301: 642050 | E301: Cocktail Server | F301: Beverage | G301: Cocktail Servers Overtime
A302: 64200R | B302: 64200 | D302: 643000 | E302: Sommelier | F302: Beverage | G302: Cocktail Servers Regular Pay
A303: 64200OT | B303: 64200 | D303: 643000 | E303: Sommelier | F303: Beverage | G303: Cocktail Servers Overtime
A304: 66100R | B304: 66100 | C304: 10 Café | D304: 661000 | E304: Cafe Barista | F304: Café | G304: Barista Regular Pay
A305: 66100OT | B305: 66100 | C305: 10 Café | D305: 661000 | E305: Cafe Barista | F305: Café | G305: Barista Overtime
A306: 66105R | B306: 66105 | C306: 10 Café | D306: 661050 | E306: Cafe Manager | F306: Café | G306: Espresso Manager Regular Pay
A307: 66105OT | B307: 66105 | C307: 10 Café | D307: 661050 | E307: Cafe Manager | F307: Café | G307: Espresso Manager Overtime
A308: 68000R | B308: 68000 | D308: 680000 | E308: Marketplace | F308: Tenant | G308: Cashiers - Gift Shop Regular Pay
A309: 68000OT | B309: 68000 | D309: 680000 | E309: Marketplace | F309: Tenant | G309: Cashiers - Gift Shop Overtime
A310: 68100R | B310: 68100 | D310: 681000 | E310: Parking Supervisors | F310: Tenant | G310: Parking Supervisors Regular Pay
A311: 68100OT | B311: 68100 | D311: 681000 | E311: Parking Supervisors | F311: Tenant | G311: Parking Supervisors Overtime
A312: 68101R | B312: 68101 | D312: 681010 | E312: Parking Attendants | F312: Tenant | G312: Parking Attendants Regular Pay
A313: 68101OT | B313: 68101 | D313: 681010 | E313: Parking Attendants | F313: Tenant | G313: Parking Attendants Overtime
A314: 68230R | B314: 68230 | D314: 682300 | E314: Tenant Janitory | F314: Tenant | G314: Janitor - Tenant Regular Pay
A315: 68230OT | B315: 68230 | D315: 682300 | E315: Tenant Janitory | F315: Tenant | G315: Janitor - Tenant Overtime
A316: 68232R | B316: 68232 | D316: 682320 | E316: Tenant Wages | F316: Tenant | G316: On Site Wages Regular Pay
A317: 68232OT | B317: 68232 | D317: 682320 | E317: Tenant Wages | F317: Tenant | G317: On Site Wages Overtime
A318: 69000R | B318: 69000 | D318: 690000 | E318: Spa Management | F318: Recreation/Amenities | G318: Spa Management Regular Pay
A319: 69000OT | B319: 69000 | D319: 690000 | E319: Spa Management | F319: Recreation/Amenities | G319: Spa Management Overtime
... A423: 88200OT | B423: 88200 | D423: 882001 | E423: Overnight Laundry Department | F423: Laundry (Select hotels) | G423: Laundry Labor - Overtime
A424: 88400R | B424: 88400 | D424: 884000 | E424: Staff Dining Manager | G424: Staff Dining Manager Regular Pay
A425: 88400OT | B425: 88400 | D425: 884000 | E425: Staff Dining Manager | G425: Staff Dining Manager Overtime Pay
A426: 88401R | B426: 88401 | D426: 884010 | E426: Staff Dining Attendant | G426: Staff Dining Attendant Regular Pay
A427: 88401OT | B427: 88401 | D427: 884010 | E427: Staff Dining Attendant | G427: Staff Dining Attendant Overtime Pay
A428: 88402R | B428: 88402 | D428: 884020 | E428: Staff Dining Cook | G428: Staff Dining Cook Regular Pay
A429: 88402OT | B429: 88402 | D429: 884020 | E429: Staff Dining Cook | G429: Staff Dining Cook Overtime Pay
P430: 2175.45
P431: =+P430-258.9-201.56 -> 1714.99
P432: =+P430-P431 -> 460.46

Sheet IncomeStatement
B1: Hotel Equities Group, LLC
B2: Hotel Equities Group (Parent) : Hotels : The Hotel Group : Seattle Tower I LLC : The Sound Hotel Seattle Belltown, Tapestry Collection by Hilton
B3: Income Statement
B4: May 2026, Jun 2026, Jul 2026
C6: May 2026 | D6: Jun 2026 | E6: Jul 2026 | F6: Total
C7: Amount | D7: Amount | E7: Amount | F7: Amount
A8: Ordinar | B8: Ordinary Income/Expense
A9: Income | B9: Income
A10: 40025 - | B10: 40025 - Retail | C10: 201980.78 | D10: 288072.05 | E10: 327273.7 | F10: =SUM(C10:E10) -> 817326.53
A11: 40060 - | B11: 40060 - Discount | C11: 412484.98 | D11: 565569.33 | E11: 615785.99 | F11: =SUM(C11:E11) -> 1593840.3
A12: 40075 - | B12: 40075 - Negotiated -Corporate | C12: 265292.99 | D12: 262838.47 | E12: 216718.06 | F12: =SUM(C12:E12) -> 744849.52
A13: 40085 - | B13: 40085 - Negotiated - Local | C13: 13953.57 | D13: 21318.9 | E13: 12937 | F13: =SUM(C13:E13) -> 48209.47
A14: 40210 - | B14: 40210 - Qualified | C14: 40164 | D14: 10675.4 | E14: 14668 | F14: =SUM(C14:E14) -> 65507.4
A15: 40225 - | B15: 40225 - Wholesale | C15: 8669.4 | D15: 25121.64 | E15: 29907.45 | F15: =SUM(C15:E15) -> 63698.49
A16: 40310 - | B16: 40310 - Corporate | C16: 4980 | D16: 28579 | E16: 54915 | F16: =SUM(C16:E16) -> 88474
A17: 40410 - | B17: 40410 - Association/Convention | C17: 0 | D17: 0 | E17: 33846.14 | F17: =SUM(C17:E17) -> 33846.14
A18: 40460 - | B18: 40460 - SMERF | C18: 18403 | D18: 13851 | E18: 4606 | F18: =SUM(C18:E18) -> 36860
A19: 40630 - | B19: 40630 - Other Room Revenue | C19: 4075.13 | D19: 5531.68 | E19: 7866.74 | F19: =SUM(C19:E19) -> 17473.55
A20: 40950 - | B20: 40950 - Room Revenue Allowance | C20: -470 | D20: -110 | E20: -599.8 | F20: =SUM(C20:E20) -> -1179.8
A21: 40970 - | B21: 40970 - Cancellation Fees - Hotel | C21: 2774.54 | D21: 3182.35 | E21: 2857.1 | F21: =SUM(C21:E21) -> 8813.99
... A44: 48108 - | B44: 48108 - Valet Parking Revenue | C44: 26157.86 | D44: 24894.89 | E44: 31294.39 | F44: =SUM(C44:E44) -> 82347.14
A45: Total - | B45: Total - Income | C45: =SUM(C10:C44) -> 1119360.2 | D45: =SUM(D10:D44) -> 1389834.3 | E45: =SUM(E10:E44) -> 1501051.6 | F45: =SUM(F10:F44) -> 4010246.1
A46: Cost Of | B46: Cost Of Sales
A47: 51000 - | B47: 51000 - Cost of Local Calls | C47: 1791.64 | D47: 1745.03 | E47: 1807.88 | F47: =SUM(C47:E47) -> 5344.55
A48: 51920 - | B48: 51920 - IT-Cost of Cell Phones | C48: 0 | D48: 875 | E48: 875 | F48: =SUM(C48:E48) -> 1750
A49: 51950 - | B49: 51950 - IT-Cost of Internet Services | C49: 3836.61 | D49: 2270.48 | E49: 2127.06 | F49: =SUM(C49:E49) -> 8234.15
A50: 52100 - | B50: 52100 - Valet Laundry Cost | C50: 578 | D50: 392.56 | E50: 681.97 | F50: =SUM(C50:E50) -> 1652.53
A51: 52250 - | B51: 52250 - Cost of Gift Shop | C51: 7521.77 | D51: 6363.66 | E51: 6819.83 | F51: =SUM(C51:E51) -> 20705.26
A52: 52251 - | B52: 52251 - Cost of Gift Shop - Liquor | C52: 195.64 | D52: 252.89 | E52: 232.54 | F52: =SUM(C52:E52) -> 681.07
A53: 52252 - | B53: 52252 - Cost of Gift Shop - Beer | C53: 219.26 | D53: 289.15 | E53: 248.85 | F53: =SUM(C53:E53) -> 757.26
A54: 52253 - | B54: 52253 - Cost of Gift Shop - Wine | C54: 373.28 | D54: 455.63 | E54: 881 | F54: =SUM(C54:E54) -> 1709.91
A55: 53000 - | B55: 53000 - Cost of Food | C55: 11917.29 | D55: 17900.16 | E55: 16465.72 | F55: =SUM(C55:E55) -> 46283.17
A56: 54100 - | B56: 54100 - Cost of Liquor | C56: 3168.17 | D56: 2441.06 | E56: 3230.67 | F56: =SUM(C56:E56) -> 8839.9
A57: 54200 - | B57: 54200 - Cost of Wine | C57: 1097.03 | D57: 1003.04 | E57: 802.98 | F57: =SUM(C57:E57) -> 2903.05
A58: 54300 - | B58: 54300 - Cost of Beer | C58: 996.23 | D58: 1665.07 | E58: 1431.49 | F58: =SUM(C58:E58) -> 4092.79
A59: Total - | B59: Total - Cost Of Sales | C59: =SUM(C47:C58) -> 31694.92 | D59: =SUM(D47:D58) -> 35653.73 | E59: =SUM(E47:E58) -> 35604.99 | F59: =SUM(F47:F58) -> 102953.64
A60: Gross P | B60: Gross Profit | C60: =C45-C59 -> 1087665.3 | D60: =D45-D59 -> 1354180.5 | E60: =E45-E59 -> 1465446.6 | F60: =F45-F59 -> 3907292.5
A61: Expense | B61: Expense
A62: 60000S | B62: 60000S - Night Auditor
A63: 60000OT | B63: 60000OT - Night Auditor Overtime | C63: 92.39 | D63: 108.71 | E63: 154.91 | F63: =SUM(C63:E63) -> 356.01
A64: 60000R | B64: 60000R - Night Auditor Regular Pay | C64: 9177.36 | D64: 9322.13 | E64: 9557.96 | F64: =SUM(C64:E64) -> 28057.45
A65: Total - | B65: Total - 60000S - Night Auditor | C65: =SUM(C63:C64) -> 9269.75 | D65: =SUM(D63:D64) -> 9430.84 | E65: =SUM(E63:E64) -> 9712.87 | F65: =SUM(F63:F64) -> 28413.46
A66: 60010S | B66: 60010S - Guest Service Manager
A67: 60010R | B67: 60010R - Guest Service Manager Regular Pay | C67: 7228.14 | D67: 6668.54 | E67: 6840.14 | F67: =SUM(C67:E67) -> 20736.82
A68: Total - | B68: Total - 60010S - Guest Service Manager | C68: =SUM(C67) -> 7228.14 | D68: =SUM(D67) -> 6668.54 | E68: =SUM(E67) -> 6840.14 | F68: =SUM(F67) -> 20736.82
A69: 60020S | B69: 60020S - Rooms Division Manager
A70: 60020R | B70: 60020R - Rooms Division Manager Regular Pay | C70: 9368.13 | D70: 8642.86 | E70: 9125.18 | F70: =SUM(C70:E70) -> 27136.17
A71: Total - | B71: Total - 60020S - Rooms Division Manager | C71: =SUM(C70) -> 9368.13 | D71: =SUM(D70) -> 8642.86 | E71: =SUM(E70) -> 9125.18 | F71: =SUM(F70) -> 27136.17
A72: 60040S | B72: 60040S - Guest Service Supervisor
A73: 60040OT | B73: 60040OT - Guest Service Supervisor Overtime | C73: 68.55 | D73: 88.32 | E73: 25.51 | F73: =SUM(C73:E73) -> 182.38
A74: 60040R | B74: 60040R - Guest Service Supervisor Regular Pay | C74: 9306.99 | D74: 8571.74 | E74: 4166.97 | F74: =SUM(C74:E74) -> 22045.7
A75: Total - | B75: Total - 60040S - Guest Service Supervisor | C75: =SUM(C73:C74) -> 9375.54 | D75: =SUM(D73:D74) -> 8660.06 | E75: =SUM(E73:E74) -> 4192.48 | F75: =SUM(F73:F74) -> 22228.08
A76: 60050S | B76: 60050S - Guest Service Representatives
A77: 60050OT | B77: 60050OT - Guest Service Representatives Overtime | C77: 7.23 | D77: 14.06 | E77: 0 | F77: =SUM(C77:E77) -> 21.29
A78: 60050R | B78: 60050R - Guest Service Representatives Regular Pay | C78: 14267.57 | D78: 13730.72 | E78: 18068.01 | F78: =SUM(C78:E78) -> 46066.3
A79: Total - | B79: Total - 60050S - Guest Service Representatives | C79: =SUM(C77:C78) -> 14274.8 | D79: =SUM(D77:D78) -> 13744.78 | E79: =SUM(E77:E78) -> 18068.01 | F79: =SUM(F77:F78) -> 46087.59
A80: 60200S | B80: 60200S - Concierge
A81: 60200OT | B81: 60200OT - Concierge Overtime | C81: 30.5 | D81: 79.39 | E81: 142.51 | F81: =SUM(C81:E81) -> 252.4
A82: 60200R | B82: 60200R - Concierge Regular Pay | C82: 8191.17 | D82: 8087.7 | E82: 4349 | F82: =SUM(C82:E82) -> 20627.87
A83: Total - | B83: Total - 60200S - Concierge | C83: =SUM(C81:C82) -> 8221.67 | D83: =SUM(D81:D82) -> 8167.09 | E83: =SUM(E81:E82) -> 4491.51 | F83: =SUM(F81:F82) -> 20880.27
A84: 60300S | B84: 60300S - Executive Housekeeper
A85: 60300R | B85: 60300R - Executive Housekeeper Regular Pay | C85: 7453.37 | D85: 6876.34 | E85: 7403.38 | F85: =SUM(C85:E85) -> 21733.09
A86: Total - | B86: Total - 60300S - Executive Housekeeper | C86: =SUM(C85) -> 7453.37 | D86: =SUM(D85) -> 6876.34 | E86: =SUM(E85) -> 7403.38 | F86: =SUM(F85) -> 21733.09
A87: 60350S | B87: 60350S - Room Attendants
A88: 60350OT | B88: 60350OT - Room Attendants Overtime | C88: 0 | D88: 0.69 | E88: 375.13 | F88: =SUM(C88:E88) -> 375.82
A89: 60350R | B89: 60350R - Room Attendants Regular Pay | C89: 57337.34 | D89: 51418.03 | E89: 60041.28 | F89: =SUM(C89:E89) -> 168796.65
A90: Total - | B90: Total - 60350S - Room Attendants | C90: =SUM(C88:C89) -> 57337.34 | D90: =SUM(D88:D89) -> 51418.72 | E90: =SUM(E88:E89) -> 60416.41 | F90: =SUM(F88:F89) -> 169172.47
A91: 60390S | B91: 60390S - Inspectors
A92: 60390R | B92: 60390R - Inspectors Regular Pay | C92: 11506.79 | D92: 11524.29 | E92: 11671.72 | F92: =SUM(C92:E92) -> 34702.8
A93: Total - | B93: Total - 60390S - Inspectors | C93: =SUM(C92) -> 11506.79 | D93: =SUM(D92) -> 11524.29 | E93: =SUM(E92) -> 11671.72 | F93: =SUM(F92) -> 34702.8
A94: 60500S | B94: 60500S - Laundry Person
A95: 60500R | B95: 60500R - Laundry Persons Regular Pay | C95: 0 | D95: 0 | E95: 219.13 | F95: =SUM(C95:E95) -> 219.13
A96: Total - | B96: Total - 60500S - Laundry Person | C96: =SUM(C95) -> 0 | D96: =SUM(D95) -> 0 | E96: =SUM(E95) -> 219.13 | F96: =SUM(F95) -> 219.13
A97: 60650S | B97: 60650S - House Person
A98: 60650R | B98: 60650R - House Persons Regular Pay | C98: 12635.45 | D98: 10831.45 | E98: 12759.57 | F98: =SUM(C98:E98) -> 36226.47
A99: Total - | B99: Total - 60650S - House Person | C99: =SUM(C98) -> 12635.45 | D99: =SUM(D98) -> 10831.45 | E99: =SUM(E98) -> 12759.57 | F99: =SUM(F98) -> 36226.47
A100: 60680 - | B100: 60680 - Service Charge Distribution - Rooms | C100: 37.8 | D100: 12.2 | E100: 0 | F100: =SUM(C100:E100) -> 50
A101: 60700 - | B101: 60700 - Bonuses and Incentives - Rooms | C101: 1672.61 | D101: 1921.03 | E101: 3672.42 | F101: =SUM(C101:E101) -> 7266.06
A102: 60920 - | B102: 60920 - Payroll Taxes-Rooms | C102: 13712.68 | D102: 12614.88 | E102: 12985.59 | F102: =SUM(C102:E102) -> 39313.15
A103: 60940 - | B103: 60940 - Benefits-Rooms | C103: 11274 | D103: 16967.67 | E103: 17157.48 | F103: =SUM(C103:E103) -> 45399.15
A104: 60960 - | B104: 60960 - Workers Compensation-Rooms | C104: 6591.82 | D104: 4353.95 | E104: 3406.99 | F104: =SUM(C104:E104) -> 14352.76
A105: 60990 - | B105: 60990 - Supplemental Pay-Rooms | C105: 5658.88 | D105: 8321.43 | E105: 3413.81 | F105: =SUM(C105:E105) -> 17394.12
A106: 61060 - | B106: 61060 - Complimentary In-Room Entertain | C106: 2032.75 | D106: 2032.75 | E106: 2114.25 | F106: =SUM(C106:E106) -> 6179.75
A107: 61165 - | B107: 61165 - Dues and Subscriptions | C107: 12.15 | D107: 12.15 | E107: 12.15 | F107: =SUM(C107:E107) -> 36.45
A108: 61220 - | B108: 61220 - Reservation Assessments | C108: 6196.96 | D108: 4730.27 | E108: 4612.88 | F108: =SUM(C108:E108) -> 15540.11
A109: 61260 - | B109: 61260 - Complimentary Food and Beverage | C109: 8482.8 | D109: 9897.02 | E109: 12162.3 | F109: =SUM(C109:E109) -> 30542.12
A110: 61310 - | B110: 61310 - Complimentary Services and Gifts - Rooms | C110: 793.91 | D110: 105.34 | E110: 509.14 | F110: =SUM(C110:E110) -> 1408.39
A111: 61340 - | B111: 61340 - Printing and Stationery | C111: 1444.82 | D111: 1356.45 | E111: 1770.82 | F111: =SUM(C111:E111) -> 4572.09
... A120: 61955 - | B120: 61955 - Uniform Laundry - Rooms | C120: 427.65 | D120: 504.38 | E120: 461.96 | F120: =SUM(C120:E120) -> 1393.99
A121: 62000S | B121: 62000S - Food & Beverage Manager
A122: 62000R | B122: 62000R - Food & Beverage Manager Regular Pay | C122: 7266.48 | D122: 9793.96 | E122: 9728.25 | F122: =SUM(C122:E122) -> 26788.69
A123: Total - | B123: Total - 62000S - Food & Beverage Manager | C123: =SUM(C122) -> 7266.48 | D123: =SUM(D122) -> 9793.96 | E123: =SUM(E122) -> 9728.25 | F123: =SUM(F122) -> 26788.69
A124: 62050S | B124: 62050S - Executive Chef
A125: 62050R | B125: 62050R - Executive Chef Regular Pay | C125: 7318.68 | D125: 7071.44 | E125: 7613.41 | F125: =SUM(C125:E125) -> 22003.53
A126: Total - | B126: Total - 62050S - Executive Chef | C126: =SUM(C125) -> 7318.68 | D126: =SUM(D125) -> 7071.44 | E126: =SUM(E125) -> 7613.41 | F126: =SUM(F125) -> 22003.53
A127: 62110S | B127: 62110S - Service Manager
A128: 62110R | B128: 62110R - Service Manager Regular Pay | C128: 7000.54 | D128: 5826.27 | E128: 6684.41 | F128: =SUM(C128:E128) -> 19511.22
A129: Total - | B129: Total - 62110S - Service Manager | C129: =SUM(C128) -> 7000.54 | D129: =SUM(D128) -> 5826.27 | E129: =SUM(E128) -> 6684.41 | F129: =SUM(F128) -> 19511.22
A130: 62115S | B130: 62115S - Asst. Service Manager
A131: 62115R | B131: 62115R - Asst. Service Manager Regular Pay | C131: 1275.71 | D131: 25.68 | E131: -120.89 | F131: =SUM(C131:E131) -> 1180.5
...
